google_ads_report/__init__.py
google_ads_report/base_client.py
google_ads_report/google_ads_client.py
google_ads_report/google_search_ads_client.py
google_ads_report-0.4.0.dist-info/LICENSE
google_ads_report-0.4.0.dist-info/METADATA
google_ads_report-0.4.0.dist-info/WHEEL
google_ads_report-0.4.0.dist-info/RECORD
